holytransaction/__init__.py
holytransaction/config.py
holytransaction/tests.py
HolyTransaction-0.1.dist-info/DESCRIPTION.rst
HolyTransaction-0.1.dist-info/METADATA
HolyTransaction-0.1.dist-info/metadata.json
HolyTransaction-0.1.dist-info/RECORD
HolyTransaction-0.1.dist-info/top_level.txt
HolyTransaction-0.1.dist-info/WHEEL
