Metadata-Version: 2.0
Name: HolyTransaction
Version: 0.1
Summary: Python client for HolyTransaction API
Home-page: https://bitbucket.org/noveltylab/ht-client-python
Author: Andrey Zamovskiy
Author-email: andrey@noveltylab.com
License: MIT
Platform: UNKNOWN
Classifier: Development Status :: 2 - Pre-Alpha
Classifier: Environment :: Console
Classifier: Environment :: Web Environment
Classifier: Intended Audience :: Developers
Classifier: License :: OSI Approved :: MIT License
Classifier: Operating System :: MacOS :: MacOS X
Classifier: Operating System :: Microsoft :: Windows
Classifier: Operating System :: POSIX
Classifier: Programming Language :: Python
Classifier: Topic :: Software Development :: Libraries :: Python Modules
Requires-Dist: httplib2 (>=0.8)
Requires-Dist: requests (>=1.1.0)
